Metadata-Version: 1.0
Name: pystatuscake
Version: 0.1.0
Summary: an alternative statuscake, more command line, more simple
Home-page: https://github.com/volodymyrss/pystatuscake.git
Author: Volodymyr Savchenko
Author-email: vladimir.savchenko@gmail.com
License: UNKNOWN
Platform: UNKNOWN
